{
	"annotations": {
		"list": [
			{
				"$$hashKey": "object:1058",
				"builtIn": 1,
				"datasource": "Prometheus",
				"enable": true,
				"hide": false,
				"iconColor": "rgba(0, 211, 255, 1)",
				"limit": 100,
				"name": "Annotations & Alerts",
				"showIn": 0,
				"type": "dashboard"
			}
		]
	},
	"description": "If NHD is present in the name of a metric or row that means it is Not Host Dependent",
	"editable": true,
	"gnetId": 1860,
	"graphTooltip": 1,
	"id": 1,
	"iteration": 1629489034415,
	"links": [],
	"panels": [
		{
			"collapsed": false,
			"datasource": "Prometheus",
			"gridPos": {
				"h": 1,
				"w": 24,
				"x": 0,
				"y": 0
			},
			"id": 261,
			"panels": [],
			"repeat": null,
			"title": "Quick CPU / Mem / Disk / Net / Pods",
			"type": "row"
		},
		{
			"datasource": null,
			"fieldConfig": {
				"defaults": {
					"color": {
						"mode": "thresholds"
					},
					"mappings": [],
					"thresholds": {
						"mode": "absolute",
						"steps": [
							{
								"color": "dark-green",
								"value": null
							},
							{
								"color": "#EAB839",
								"value": 50
							},
							{
								"color": "semi-dark-red",
								"value": 75
							}
						]
					},
					"unit": "percent"
				},
				"overrides": []
			},
			"gridPos": {
				"h": 5,
				"w": 3,
				"x": 0,
				"y": 1
			},
			"id": 360,
			"options": {
				"reduceOptions": {
					"calcs": [
						"lastNotNull"
					],
					"fields": "",
					"values": false
				},
				"showThresholdLabels": false,
				"showThresholdMarkers": true,
				"text": {}
			},
			"pluginVersion": "7.5.4",
			"targets": [
				{
					"exemplar": true,
					"expr": "sum(irate(node_cpu_seconds_total{instance='$node',job='$job',mode!='idle'}[5m])) / sum(irate(node_cpu_seconds_total{instance='$node',job='$job',}[5m])) * 100",
					"interval": "",
					"legendFormat": "",
					"refId": "A"
				}
			],
			"title": "CPU Busy (5m)",
			"type": "gauge"
		},
		{
			"cacheTimeout": null,
			"datasource": "Prometheus",
			"description": "Busy state of all CPU cores together (5 min average)",
			"fieldConfig": {
				"defaults": {
					"color": {
						"mode": "thresholds"
					},
					"mappings": [
						{
							"id": 0,
							"op": "=",
							"text": "N/A",
							"type": 1,
							"value": "null"
						}
					],
					"max": 100,
					"min": 0,
					"thresholds": {
						"mode": "absolute",
						"steps": [
							{
								"color": "rgba(50, 172, 45, 0.97)",
								"value": null
							},
							{
								"color": "rgba(237, 129, 40, 0.89)",
								"value": 85
							},
							{
								"color": "rgba(245, 54, 54, 0.9)",
								"value": 95
							}
						]
					},
					"unit": "percent"
				},
				"overrides": []
			},
			"gridPos": {
				"h": 5,
				"w": 3,
				"x": 3,
				"y": 1
			},
			"id": 155,
			"links": [],
			"options": {
				"orientation": "horizontal",
				"reduceOptions": {
					"calcs": [
						"lastNotNull"
					],
					"fields": "",
					"values": false
				},
				"showThresholdLabels": false,
				"showThresholdMarkers": true,
				"text": {}
			},
			"pluginVersion": "7.5.4",
			"targets": [
				{
					"expr": "avg(node_load5{instance=\"$node\",job=\"$job\"}) /  count(count(node_cpu_seconds_total{instance=\"$node\",job=\"$job\"}) by (cpu)) * 100",
					"format": "time_series",
					"hide": false,
					"intervalFactor": 1,
					"refId": "A",
					"step": 900
				}
			],
			"title": "Sys Load (5m avg)",
			"type": "gauge"
		},
		{
			"cacheTimeout": null,
			"datasource": "Prometheus",
			"description": "Busy state of all CPU cores together (15 min average)",
			"fieldConfig": {
				"defaults": {
					"color": {
						"mode": "thresholds"
					},
					"mappings": [
						{
							"id": 0,
							"op": "=",
							"text": "N/A",
							"type": 1,
							"value": "null"
						}
					],
					"max": 100,
					"min": 0,
					"thresholds": {
						"mode": "absolute",
						"steps": [
							{
								"color": "rgba(50, 172, 45, 0.97)",
								"value": null
							},
							{
								"color": "rgba(237, 129, 40, 0.89)",
								"value": 85
							},
							{
								"color": "rgba(245, 54, 54, 0.9)",
								"value": 95
							}
						]
					},
					"unit": "percent"
				},
				"overrides": []
			},
			"gridPos": {
				"h": 5,
				"w": 3,
				"x": 6,
				"y": 1
			},
			"id": 19,
			"links": [],
			"options": {
				"orientation": "horizontal",
				"reduceOptions": {
					"calcs": [
						"lastNotNull"
					],
					"fields": "",
					"values": false
				},
				"showThresholdLabels": false,
				"showThresholdMarkers": true,
				"text": {}
			},
			"pluginVersion": "7.5.4",
			"targets": [
				{
					"expr": "avg(node_load15{instance=\"$node\",job=\"$job\"}) /  count(count(node_cpu_seconds_total{instance=\"$node\",job=\"$job\"}) by (cpu)) * 100",
					"hide": false,
					"intervalFactor": 1,
					"refId": "A",
					"step": 900
				}
			],
			"title": "Sys Load (15m avg)",
			"type": "gauge"
		},
		{
			"cacheTimeout": null,
			"datasource": "Prometheus",
			"description": "Non available RAM memory",
			"fieldConfig": {
				"defaults": {
					"color": {
						"mode": "thresholds"
					},
					"mappings": [],
					"thresholds": {
						"mode": "absolute",
						"steps": [
							{
								"color": "green",
								"value": null
							},
							{
								"color": "red",
								"value": 80
							}
						]
					},
					"unit": "percent"
				},
				"overrides": []
			},
			"gridPos": {
				"h": 5,
				"w": 3,
				"x": 9,
				"y": 1
			},
			"hideTimeOverride": false,
			"id": 16,
			"links": [],
			"options": {
				"orientation": "horizontal",
				"reduceOptions": {
					"calcs": [
						"lastNotNull"
					],
					"fields": "",
					"values": false
				},
				"showThresholdLabels": false,
				"showThresholdMarkers": true,
				"text": {}
			},
			"pluginVersion": "7.5.4",
			"targets": [
				{
					"expr": "((node_memory_MemTotal_bytes{instance=\"$node\",job=\"$job\"} - node_memory_MemFree_bytes{instance=\"$node\",job=\"$job\"}) / (node_memory_MemTotal_bytes{instance=\"$node\",job=\"$job\"} )) * 100",
					"format": "time_series",
					"hide": true,
					"intervalFactor": 1,
					"refId": "A",
					"step": 900
				},
				{
					"expr": "100 - ((node_memory_MemAvailable_bytes{instance=\"$node\",job=\"$job\"} * 100) / node_memory_MemTotal_bytes{instance=\"$node\",job=\"$job\"})",
					"format": "time_series",
					"hide": false,
					"intervalFactor": 1,
					"refId": "B",
					"step": 900
				}
			],
			"timeFrom": null,
			"timeShift": null,
			"title": "RAM Used",
			"type": "gauge"
		},
		{
			"cacheTimeout": null,
			"datasource": "Prometheus",
			"description": "Used Swap",
			"fieldConfig": {
				"defaults": {
					"color": {
						"mode": "thresholds"
					},
					"mappings": [
						{
							"id": 0,
							"op": "=",
							"text": "N/A",
							"type": 1,
							"value": "null"
						}
					],
					"max": 100,
					"min": 0,
					"thresholds": {
						"mode": "absolute",
						"steps": [
							{
								"color": "rgba(50, 172, 45, 0.97)",
								"value": null
							},
							{
								"color": "rgba(237, 129, 40, 0.89)",
								"value": 10
							},
							{
								"color": "rgba(245, 54, 54, 0.9)",
								"value": 25
							}
						]
					},
					"unit": "percent"
				},
				"overrides": []
			},
			"gridPos": {
				"h": 5,
				"w": 3,
				"x": 12,
				"y": 1
			},
			"id": 21,
			"links": [],
			"options": {
				"orientation": "horizontal",
				"reduceOptions": {
					"calcs": [
						"lastNotNull"
					],
					"fields": "",
					"values": false
				},
				"showThresholdLabels": false,
				"showThresholdMarkers": true,
				"text": {}
			},
			"pluginVersion": "7.5.4",
			"targets": [
				{
					"expr": "((node_memory_SwapTotal_bytes{instance=\"$node\",job=\"$job\"} - node_memory_SwapFree_bytes{instance=\"$node\",job=\"$job\"}) / (node_memory_SwapTotal_bytes{instance=\"$node\",job=\"$job\"} )) * 100",
					"intervalFactor": 1,
					"refId": "A",
					"step": 900
				}
			],
			"title": "SWAP Used ( MUST BE N/A )",
			"type": "gauge"
		},
		{
			"cacheTimeout": null,
			"datasource": "Prometheus",
			"description": "Used Root FS",
			"fieldConfig": {
				"defaults": {
					"color": {
						"mode": "thresholds"
					},
					"mappings": [
						{
							"id": 0,
							"op": "=",
							"text": "N/A",
							"type": 1,
							"value": "null"
						}
					],
					"max": 100,
					"min": 0,
					"thresholds": {
						"mode": "absolute",
						"steps": [
							{
								"color": "rgba(50, 172, 45, 0.97)",
								"value": null
							},
							{
								"color": "rgba(237, 129, 40, 0.89)",
								"value": 80
							},
							{
								"color": "rgba(245, 54, 54, 0.9)",
								"value": 90
							}
						]
					},
					"unit": "percent"
				},
				"overrides": []
			},
			"gridPos": {
				"h": 5,
				"w": 3,
				"x": 15,
				"y": 1
			},
			"id": 154,
			"links": [],
			"options": {
				"orientation": "horizontal",
				"reduceOptions": {
					"calcs": [
						"lastNotNull"
					],
					"fields": "",
					"values": false
				},
				"showThresholdLabels": false,
				"showThresholdMarkers": true,
				"text": {}
			},
			"pluginVersion": "7.5.4",
			"targets": [
				{
					"exemplar": true,
					"expr": "100 - ((node_filesystem_avail_bytes{instance=\"$node\",job=\"$job\",mountpoint=\"/\",fstype!=\"rootfs\"} * 100) / node_filesystem_size_bytes{instance=\"$node\",job=\"$job\",mountpoint=\"/\",fstype!=\"rootfs\"})",
					"format": "time_series",
					"interval": "",
					"intervalFactor": 1,
					"legendFormat": "",
					"refId": "A",
					"step": 900
				}
			],
			"title": "Disk Utilization",
			"type": "gauge"
		},
		{
			"cacheTimeout": null,
			"colorBackground": false,
			"colorValue": false,
			"colors": [
				"rgba(245, 54, 54, 0.9)",
				"rgba(237, 129, 40, 0.89)",
				"rgba(50, 172, 45, 0.97)"
			],
			"datasource": "Prometheus",
			"decimals": 0,
			"description": "Total RAM",
			"fieldConfig": {
				"defaults": {},
				"overrides": []
			},
			"format": "bytes",
			"gauge": {
				"maxValue": 100,
				"minValue": 0,
				"show": false,
				"thresholdLabels": false,
				"thresholdMarkers": true
			},
			"gridPos": {
				"h": 5,
				"w": 2,
				"x": 18,
				"y": 1
			},
			"id": 75,
			"interval": null,
			"links": [],
			"mappingType": 1,
			"mappingTypes": [
				{
					"name": "value to text",
					"value": 1
				},
				{
					"name": "range to text",
					"value": 2
				}
			],
			"maxDataPoints": 100,
			"maxPerRow": 6,
			"nullPointMode": "null",
			"nullText": null,
			"postfix": "",
			"postfixFontSize": "70%",
			"prefix": "",
			"prefixFontSize": "50%",
			"rangeMaps": [
				{
					"from": "null",
					"text": "N/A",
					"to": "null"
				}
			],
			"sparkline": {
				"fillColor": "rgba(31, 118, 189, 0.18)",
				"full": false,
				"lineColor": "rgb(31, 120, 193)",
				"show": false
			},
			"tableColumn": "",
			"targets": [
				{
					"expr": "node_memory_MemTotal_bytes{instance=\"$node\",job=\"$job\"}",
					"intervalFactor": 1,
					"refId": "A",
					"step": 900
				}
			],
			"thresholds": "",
			"title": "RAM Total",
			"type": "singlestat",
			"valueFontSize": "50%",
			"valueMaps": [
				{
					"op": "=",
					"text": "N/A",
					"value": "null"
				}
			],
			"valueName": "current"
		},
		{
			"cacheTimeout": null,
			"colorBackground": false,
			"colorValue": false,
			"colors": [
				"rgba(245, 54, 54, 0.9)",
				"rgba(237, 129, 40, 0.89)",
				"rgba(50, 172, 45, 0.97)"
			],
			"datasource": "Prometheus",
			"decimals": 1,
			"description": "System uptime",
			"fieldConfig": {
				"defaults": {},
				"overrides": []
			},
			"format": "s",
			"gauge": {
				"maxValue": 100,
				"minValue": 0,
				"show": false,
				"thresholdLabels": false,
				"thresholdMarkers": true
			},
			"gridPos": {
				"h": 5,
				"w": 2,
				"x": 20,
				"y": 1
			},
			"hideTimeOverride": true,
			"id": 15,
			"interval": null,
			"links": [],
			"mappingType": 1,
			"mappingTypes": [
				{
					"$$hashKey": "object:1094",
					"name": "value to text",
					"value": 1
				},
				{
					"$$hashKey": "object:1095",
					"name": "range to text",
					"value": 2
				}
			],
			"maxDataPoints": 100,
			"nullPointMode": "null",
			"nullText": null,
			"postfix": "s",
			"postfixFontSize": "50%",
			"prefix": "",
			"prefixFontSize": "50%",
			"rangeMaps": [
				{
					"from": "null",
					"text": "N/A",
					"to": "null"
				}
			],
			"sparkline": {
				"fillColor": "rgba(31, 118, 189, 0.18)",
				"full": false,
				"lineColor": "rgb(31, 120, 193)",
				"show": false
			},
			"tableColumn": "",
			"targets": [
				{
					"expr": "node_time_seconds{instance=\"$node\",job=\"$job\"} - node_boot_time_seconds{instance=\"$node\",job=\"$job\"}",
					"intervalFactor": 2,
					"refId": "A",
					"step": 1800
				}
			],
			"thresholds": "",
			"title": "Uptime",
			"type": "singlestat",
			"valueFontSize": "50%",
			"valueMaps": [
				{
					"$$hashKey": "object:1097",
					"op": "=",
					"text": "N/A",
					"value": "null"
				}
			],
			"valueName": "current"
		},
		{
			"cacheTimeout": null,
			"colorBackground": false,
			"colorValue": false,
			"colors": [
				"rgba(245, 54, 54, 0.9)",
				"rgba(237, 129, 40, 0.89)",
				"rgba(50, 172, 45, 0.97)"
			],
			"datasource": "Prometheus",
			"description": "Total number of CPU cores",
			"fieldConfig": {
				"defaults": {},
				"overrides": []
			},
			"format": "short",
			"gauge": {
				"maxValue": 100,
				"minValue": 0,
				"show": false,
				"thresholdLabels": false,
				"thresholdMarkers": true
			},
			"gridPos": {
				"h": 3,
				"w": 2,
				"x": 22,
				"y": 1
			},
			"id": 14,
			"interval": null,
			"links": [],
			"mappingType": 1,
			"mappingTypes": [
				{
					"name": "value to text",
					"value": 1
				},
				{
					"name": "range to text",
					"value": 2
				}
			],
			"maxDataPoints": 100,
			"maxPerRow": 6,
			"nullPointMode": "null",
			"nullText": null,
			"postfix": "",
			"postfixFontSize": "50%",
			"prefix": "",
			"prefixFontSize": "50%",
			"rangeMaps": [
				{
					"from": "null",
					"text": "N/A",
					"to": "null"
				}
			],
			"sparkline": {
				"fillColor": "rgba(31, 118, 189, 0.18)",
				"full": false,
				"lineColor": "rgb(31, 120, 193)",
				"show": false
			},
			"tableColumn": "",
			"targets": [
				{
					"expr": "count(count(node_cpu_seconds_total{instance=\"$node\",job=\"$job\"}) by (cpu))",
					"interval": "",
					"intervalFactor": 1,
					"legendFormat": "",
					"refId": "A",
					"step": 900
				}
			],
			"thresholds": "",
			"title": "CPU Cores",
			"type": "singlestat",
			"valueFontSize": "50%",
			"valueMaps": [
				{
					"op": "=",
					"text": "N/A",
					"value": "null"
				}
			],
			"valueName": "current"
		},
		{
			"cacheTimeout": null,
			"colorBackground": false,
			"colorValue": false,
			"colors": [
				"rgba(50, 172, 45, 0.97)",
				"rgba(237, 129, 40, 0.89)",
				"rgba(245, 54, 54, 0.9)"
			],
			"datasource": "Prometheus",
			"decimals": 0,
			"description": "Total RootFS",
			"fieldConfig": {
				"defaults": {},
				"overrides": []
			},
			"format": "bytes",
			"gauge": {
				"maxValue": 100,
				"minValue": 0,
				"show": false,
				"thresholdLabels": false,
				"thresholdMarkers": true
			},
			"gridPos": {
				"h": 2,
				"w": 2,
				"x": 22,
				"y": 4
			},
			"id": 23,
			"interval": null,
			"links": [],
			"mappingType": 1,
			"mappingTypes": [
				{
					"name": "value to text",
					"value": 1
				},
				{
					"name": "range to text",
					"value": 2
				}
			],
			"maxDataPoints": 100,
			"maxPerRow": 6,
			"nullPointMode": "null",
			"nullText": null,
			"postfix": "",
			"postfixFontSize": "50%",
			"prefix": "",
			"prefixFontSize": "50%",
			"rangeMaps": [
				{
					"from": "null",
					"text": "N/A",
					"to": "null"
				}
			],
			"sparkline": {
				"fillColor": "rgba(31, 118, 189, 0.18)",
				"full": false,
				"lineColor": "rgb(31, 120, 193)",
				"show": false
			},
			"tableColumn": "",
			"targets": [
				{
					"expr": "node_filesystem_size_bytes{instance=\"$node\",job=\"$job\",mountpoint=\"/\",fstype!=\"rootfs\"}",
					"format": "time_series",
					"hide": false,
					"intervalFactor": 1,
					"refId": "A",
					"step": 900
				}
			],
			"thresholds": "70,90",
			"title": "RootFS Total",
			"type": "singlestat",
			"valueFontSize": "50%",
			"valueMaps": [
				{
					"op": "=",
					"text": "N/A",
					"value": "null"
				}
			],
			"valueName": "current"
		},
		{
			"aliasColors": {},
			"bars": false,
			"dashLength": 10,
			"dashes": false,
			"datasource": "Prometheus",
			"fieldConfig": {
				"defaults": {
					"unit": "bytes"
				},
				"overrides": []
			},
			"fill": 1,
			"fillGradient": 0,
			"gridPos": {
				"h": 8,
				"w": 12,
				"x": 0,
				"y": 6
			},
			"hiddenSeries": false,
			"id": 317,
			"legend": {
				"avg": false,
				"current": false,
				"max": false,
				"min": false,
				"show": true,
				"total": false,
				"values": false
			},
			"lines": true,
			"linewidth": 1,
			"links": [],
			"nullPointMode": "null",
			"options": {
				"alertThreshold": true
			},
			"percentage": false,
			"pluginVersion": "7.5.4",
			"pointradius": 2,
			"points": false,
			"renderer": "flot",
			"repeat": null,
			"seriesOverrides": [],
			"spaceLength": 10,
			"stack": false,
			"steppedLine": false,
			"targets": [
				{
					"exemplar": true,
					"expr": "sum(irate(node_network_receive_bytes_total{instance=~'$node'}[5m])*8)",
					"interval": "",
					"intervalFactor": 2,
					"legendFormat": "Incoming Traffic",
					"metric": "",
					"refId": "A",
					"step": 1200,
					"target": ""
				}
			],
			"thresholds": [],
			"timeFrom": null,
			"timeRegions": [],
			"timeShift": null,
			"title": "Traffic In",
			"tooltip": {
				"shared": true,
				"sort": 0,
				"value_type": "individual"
			},
			"type": "graph",
			"xaxis": {
				"buckets": null,
				"mode": "time",
				"name": null,
				"show": true,
				"values": []
			},
			"yaxes": [
				{
					"$$hashKey": "object:1662",
					"format": "bytes",
					"label": null,
					"logBase": 1,
					"max": null,
					"min": null,
					"show": true
				},
				{
					"$$hashKey": "object:1663",
					"format": "short",
					"label": null,
					"logBase": 1,
					"max": null,
					"min": null,
					"show": true
				}
			],
			"yaxis": {
				"align": false,
				"alignLevel": null
			}
		},
		{
			"aliasColors": {},
			"bars": false,
			"dashLength": 10,
			"dashes": false,
			"datasource": "Prometheus",
			"fieldConfig": {
				"defaults": {
					"unit": "bytes"
				},
				"overrides": []
			},
			"fill": 1,
			"fillGradient": 0,
			"gridPos": {
				"h": 8,
				"w": 12,
				"x": 12,
				"y": 6
			},
			"hiddenSeries": false,
			"id": 319,
			"legend": {
				"avg": false,
				"current": false,
				"max": false,
				"min": false,
				"show": true,
				"total": false,
				"values": false
			},
			"lines": true,
			"linewidth": 1,
			"links": [],
			"nullPointMode": "null",
			"options": {
				"alertThreshold": true
			},
			"percentage": false,
			"pluginVersion": "7.5.4",
			"pointradius": 2,
			"points": false,
			"renderer": "flot",
			"repeat": null,
			"seriesOverrides": [],
			"spaceLength": 10,
			"stack": false,
			"steppedLine": false,
			"targets": [
				{
					"exemplar": true,
					"expr": "sum(irate(node_network_transmit_bytes_total{instance=~'$node'}[5m])*8)",
					"interval": "",
					"intervalFactor": 2,
					"legendFormat": "Outgoing traffic",
					"refId": "B",
					"step": 1200
				}
			],
			"thresholds": [],
			"timeFrom": null,
			"timeRegions": [],
			"timeShift": null,
			"title": "Traffic Out",
			"tooltip": {
				"shared": true,
				"sort": 0,
				"value_type": "individual"
			},
			"type": "graph",
			"xaxis": {
				"buckets": null,
				"mode": "time",
				"name": null,
				"show": true,
				"values": []
			},
			"yaxes": [
				{
					"$$hashKey": "object:1745",
					"format": "bytes",
					"label": null,
					"logBase": 1,
					"max": null,
					"min": null,
					"show": true
				},
				{
					"$$hashKey": "object:1746",
					"format": "short",
					"label": null,
					"logBase": 1,
					"max": null,
					"min": null,
					"show": true
				}
			],
			"yaxis": {
				"align": false,
				"alignLevel": null
			}
		},
		{
			"aliasColors": {},
			"bars": false,
			"dashLength": 10,
			"dashes": false,
			"datasource": null,
			"description": "",
			"fieldConfig": {
				"defaults": {},
				"overrides": []
			},
			"fill": 0,
			"fillGradient": 0,
			"gridPos": {
				"h": 7,
				"w": 24,
				"x": 0,
				"y": 14
			},
			"hiddenSeries": false,
			"id": 323,
			"legend": {
				"avg": false,
				"current": false,
				"max": false,
				"min": false,
				"show": true,
				"total": false,
				"values": false
			},
			"lines": true,
			"linewidth": 1,
			"nullPointMode": "null",
			"options": {
				"alertThreshold": true
			},
			"percentage": false,
			"pluginVersion": "7.5.4",
			"pointradius": 2,
			"points": false,
			"renderer": "flot",
			"seriesOverrides": [],
			"spaceLength": 10,
			"stack": false,
			"steppedLine": false,
			"targets": [
				{
					"exemplar": true,
					"expr": "kubelet_running_pods",
					"interval": "",
					"legendFormat": "{{instance}}",
					"refId": "A"
				}
			],
			"thresholds": [],
			"timeFrom": null,
			"timeRegions": [],
			"timeShift": null,
			"title": "Running Pods Per Node NHD",
			"tooltip": {
				"shared": true,
				"sort": 0,
				"value_type": "individual"
			},
			"type": "graph",
			"xaxis": {
				"buckets": null,
				"mode": "time",
				"name": null,
				"show": true,
				"values": []
			},
			"yaxes": [
				{
					"$$hashKey": "object:2953",
					"format": "short",
					"label": "Pods",
					"logBase": 1,
					"max": null,
					"min": null,
					"show": true
				},
				{
					"$$hashKey": "object:2954",
					"format": "short",
					"label": null,
					"logBase": 1,
					"max": null,
					"min": null,
					"show": false
				}
			],
			"yaxis": {
				"align": false,
				"alignLevel": null
			}
		},
		{
			"collapsed": true,
			"datasource": null,
			"gridPos": {
				"h": 1,
				"w": 24,
				"x": 0,
				"y": 21
			},
			"id": 362,
			"panels": [
				{
					"datasource": null,
					"fieldConfig": {
						"defaults": {
							"color": {
								"mode": "thresholds"
							},
							"mappings": [],
							"max": 100,
							"min": 0,
							"noValue": "N/A",
							"thresholds": {
								"mode": "absolute",
								"steps": [
									{
										"color": "dark-green",
										"value": null
									},
									{
										"color": "dark-yellow",
										"value": 50
									},
									{
										"color": "semi-dark-red",
										"value": 75
									}
								]
							},
							"unit": "percent"
						},
						"overrides": []
					},
					"gridPos": {
						"h": 5,
						"w": 24,
						"x": 0,
						"y": 3
					},
					"id": 363,
					"options": {
						"colorMode": "value",
						"graphMode": "area",
						"justifyMode": "auto",
						"orientation": "auto",
						"reduceOptions": {
							"calcs": [
								"lastNotNull"
							],
							"fields": "",
							"values": false
						},
						"text": {},
						"textMode": "auto"
					},
					"pluginVersion": "7.5.4",
					"targets": [
						{
							"exemplar": true,
							"expr": "sum(irate(node_cpu_seconds_total{mode!='idle'}[1m])) by (instance) / sum(irate(node_cpu_seconds_total[1m])) by (instance) * 100",
							"format": "time_series",
							"interval": "",
							"legendFormat": "{{instance}}",
							"refId": "A"
						}
					],
					"timeFrom": null,
					"timeShift": null,
					"title": "CPU Busy ( 1m )",
					"type": "stat"
				},
				{
					"datasource": null,
					"fieldConfig": {
						"defaults": {
							"color": {
								"mode": "thresholds"
							},
							"mappings": [],
							"thresholds": {
								"mode": "absolute",
								"steps": [
									{
										"color": "dark-green",
										"value": null
									},
									{
										"color": "semi-dark-yellow",
										"value": 50
									},
									{
										"color": "semi-dark-red",
										"value": 75
									}
								]
							},
							"unit": "percent"
						},
						"overrides": []
					},
					"gridPos": {
						"h": 5,
						"w": 24,
						"x": 0,
						"y": 8
					},
					"id": 365,
					"options": {
						"colorMode": "value",
						"graphMode": "area",
						"justifyMode": "auto",
						"orientation": "auto",
						"reduceOptions": {
							"calcs": [
								"lastNotNull"
							],
							"fields": "",
							"values": false
						},
						"text": {},
						"textMode": "auto"
					},
					"pluginVersion": "7.5.4",
					"targets": [
						{
							"exemplar": true,
							"expr": "100 - ((node_memory_MemAvailable_bytes{job=\"$job\"} * 100) / node_memory_MemTotal_bytes{job=\"$job\"})",
							"interval": "",
							"legendFormat": "{{instance}}",
							"refId": "A"
						}
					],
					"title": "Ram used % ",
					"type": "stat"
				},
				{
					"datasource": null,
					"fieldConfig": {
						"defaults": {
							"color": {
								"mode": "thresholds"
							},
							"mappings": [],
							"thresholds": {
								"mode": "absolute",
								"steps": [
									{
										"color": "dark-green",
										"value": null
									},
									{
										"color": "semi-dark-yellow",
										"value": 50
									},
									{
										"color": "dark-red",
										"value": 75
									}
								]
							},
							"unit": "percent"
						},
						"overrides": []
					},
					"gridPos": {
						"h": 6,
						"w": 24,
						"x": 0,
						"y": 13
					},
					"id": 367,
					"options": {
						"displayMode": "gradient",
						"orientation": "auto",
						"reduceOptions": {
							"calcs": [
								"lastNotNull"
							],
							"fields": "",
							"values": false
						},
						"showUnfilled": true,
						"text": {}
					},
					"pluginVersion": "7.5.4",
					"targets": [
						{
							"exemplar": true,
							"expr": "100 - ((node_filesystem_avail_bytes{job=\"$job\",mountpoint=\"/\",fstype!=\"rootfs\"} * 100) / node_filesystem_size_bytes{job=\"$job\",mountpoint=\"/\",fstype!=\"rootfs\"})",
							"interval": "",
							"legendFormat": "{{instance}}",
							"refId": "A"
						}
					],
					"title": "Disk Used",
					"type": "bargauge"
				}
			],
			"title": "Node Metrics NHD",
			"type": "row"
		},
		{
			"collapsed": true,
			"datasource": null,
			"gridPos": {
				"h": 1,
				"w": 24,
				"x": 0,
				"y": 22
			},
			"id": 352,
			"panels": [
				{
					"aliasColors": {},
					"bars": false,
					"dashLength": 10,
					"dashes": false,
					"datasource": null,
					"description": "",
					"fieldConfig": {
						"defaults": {},
						"overrides": []
					},
					"fill": 1,
					"fillGradient": 0,
					"gridPos": {
						"h": 8,
						"w": 12,
						"x": 0,
						"y": 4
					},
					"hiddenSeries": false,
					"id": 354,
					"legend": {
						"avg": false,
						"current": false,
						"max": false,
						"min": false,
						"show": true,
						"total": false,
						"values": false
					},
					"lines": true,
					"linewidth": 1,
					"nullPointMode": "null",
					"options": {
						"alertThreshold": true
					},
					"percentage": false,
					"pluginVersion": "7.5.4",
					"pointradius": 2,
					"points": false,
					"renderer": "flot",
					"seriesOverrides": [],
					"spaceLength": 10,
					"stack": false,
					"steppedLine": false,
					"targets": [
						{
							"exemplar": true,
							"expr": "irate(node_pressure_memory_stalled_seconds_total[5m])",
							"interval": "",
							"legendFormat": "{{instance}}",
							"refId": "A"
						}
					],
					"thresholds": [],
					"timeFrom": null,
					"timeRegions": [],
					"timeShift": null,
					"title": "Node Memory Stalled Seconds Total Over 5m",
					"tooltip": {
						"shared": true,
						"sort": 0,
						"value_type": "individual"
					},
					"type": "graph",
					"xaxis": {
						"buckets": null,
						"mode": "time",
						"name": null,
						"show": true,
						"values": []
					},
					"yaxes": [
						{
							"format": "short",
							"label": null,
							"logBase": 1,
							"max": null,
							"min": null,
							"show": true
						},
						{
							"format": "short",
							"label": null,
							"logBase": 1,
							"max": null,
							"min": null,
							"show": true
						}
					],
					"yaxis": {
						"align": false,
						"alignLevel": null
					}
				},
				{
					"aliasColors": {},
					"bars": false,
					"dashLength": 10,
					"dashes": false,
					"datasource": null,
					"description": "",
					"fieldConfig": {
						"defaults": {},
						"overrides": []
					},
					"fill": 1,
					"fillGradient": 0,
					"gridPos": {
						"h": 8,
						"w": 12,
						"x": 12,
						"y": 4
					},
					"hiddenSeries": false,
					"id": 355,
					"legend": {
						"avg": false,
						"current": false,
						"max": false,
						"min": false,
						"show": true,
						"total": false,
						"values": false
					},
					"lines": true,
					"linewidth": 1,
					"nullPointMode": "null",
					"options": {
						"alertThreshold": true
					},
					"percentage": false,
					"pluginVersion": "7.5.4",
					"pointradius": 2,
					"points": false,
					"renderer": "flot",
					"seriesOverrides": [],
					"spaceLength": 10,
					"stack": false,
					"steppedLine": false,
					"targets": [
						{
							"exemplar": true,
							"expr": "irate(node_pressure_memory_waiting_seconds_total[5m])",
							"interval": "",
							"legendFormat": "{{instance}}",
							"refId": "A"
						}
					],
					"thresholds": [],
					"timeFrom": null,
					"timeRegions": [],
					"timeShift": null,
					"title": "Node Memory Waiting Seconds Total Over 5m",
					"tooltip": {
						"shared": true,
						"sort": 0,
						"value_type": "individual"
					},
					"type": "graph",
					"xaxis": {
						"buckets": null,
						"mode": "time",
						"name": null,
						"show": true,
						"values": []
					},
					"yaxes": [
						{
							"format": "short",
							"label": null,
							"logBase": 1,
							"max": null,
							"min": null,
							"show": true
						},
						{
							"format": "short",
							"label": null,
							"logBase": 1,
							"max": null,
							"min": null,
							"show": true
						}
					],
					"yaxis": {
						"align": false,
						"alignLevel": null
					}
				},
				{
					"aliasColors": {},
					"bars": false,
					"dashLength": 10,
					"dashes": false,
					"datasource": null,
					"description": "",
					"fieldConfig": {
						"defaults": {},
						"overrides": []
					},
					"fill": 1,
					"fillGradient": 0,
					"gridPos": {
						"h": 8,
						"w": 12,
						"x": 0,
						"y": 12
					},
					"hiddenSeries": false,
					"id": 356,
					"legend": {
						"avg": false,
						"current": false,
						"max": false,
						"min": false,
						"show": true,
						"total": false,
						"values": false
					},
					"lines": true,
					"linewidth": 1,
					"nullPointMode": "null",
					"options": {
						"alertThreshold": true
					},
					"percentage": false,
					"pluginVersion": "7.5.4",
					"pointradius": 2,
					"points": false,
					"renderer": "flot",
					"seriesOverrides": [],
					"spaceLength": 10,
					"stack": false,
					"steppedLine": false,
					"targets": [
						{
							"exemplar": true,
							"expr": "rate(node_pressure_io_waiting_seconds_total[5m])",
							"interval": "",
							"legendFormat": "{{instance}}",
							"refId": "A"
						}
					],
					"thresholds": [],
					"timeFrom": null,
					"timeRegions": [],
					"timeShift": null,
					"title": "Node Io Waiting Seconds Total Over 5m",
					"tooltip": {
						"shared": true,
						"sort": 0,
						"value_type": "individual"
					},
					"type": "graph",
					"xaxis": {
						"buckets": null,
						"mode": "time",
						"name": null,
						"show": true,
						"values": []
					},
					"yaxes": [
						{
							"format": "short",
							"label": null,
							"logBase": 1,
							"max": null,
							"min": null,
							"show": true
						},
						{
							"format": "short",
							"label": null,
							"logBase": 1,
							"max": null,
							"min": null,
							"show": true
						}
					],
					"yaxis": {
						"align": false,
						"alignLevel": null
					}
				},
				{
					"aliasColors": {},
					"bars": false,
					"dashLength": 10,
					"dashes": false,
					"datasource": null,
					"description": "",
					"fieldConfig": {
						"defaults": {},
						"overrides": []
					},
					"fill": 1,
					"fillGradient": 0,
					"gridPos": {
						"h": 8,
						"w": 12,
						"x": 12,
						"y": 12
					},
					"hiddenSeries": false,
					"id": 357,
					"legend": {
						"avg": false,
						"current": false,
						"max": false,
						"min": false,
						"show": true,
						"total": false,
						"values": false
					},
					"lines": true,
					"linewidth": 1,
					"nullPointMode": "null",
					"options": {
						"alertThreshold": true
					},
					"percentage": false,
					"pluginVersion": "7.5.4",
					"pointradius": 2,
					"points": false,
					"renderer": "flot",
					"seriesOverrides": [],
					"spaceLength": 10,
					"stack": false,
					"steppedLine": false,
					"targets": [
						{
							"exemplar": true,
							"expr": "rate(node_pressure_io_stalled_seconds_total[5m])",
							"interval": "",
							"legendFormat": "{{instance}}",
							"refId": "A"
						}
					],
					"thresholds": [],
					"timeFrom": null,
					"timeRegions": [],
					"timeShift": null,
					"title": "Node Io Stalled Seconds Total Over 5m",
					"tooltip": {
						"shared": true,
						"sort": 0,
						"value_type": "individual"
					},
					"type": "graph",
					"xaxis": {
						"buckets": null,
						"mode": "time",
						"name": null,
						"show": true,
						"values": []
					},
					"yaxes": [
						{
							"format": "short",
							"label": null,
							"logBase": 1,
							"max": null,
							"min": null,
							"show": true
						},
						{
							"format": "short",
							"label": null,
							"logBase": 1,
							"max": null,
							"min": null,
							"show": true
						}
					],
					"yaxis": {
						"align": false,
						"alignLevel": null
					}
				},
				{
					"aliasColors": {},
					"bars": false,
					"dashLength": 10,
					"dashes": false,
					"datasource": null,
					"description": "",
					"fieldConfig": {
						"defaults": {},
						"overrides": []
					},
					"fill": 1,
					"fillGradient": 0,
					"gridPos": {
						"h": 8,
						"w": 24,
						"x": 0,
						"y": 20
					},
					"hiddenSeries": false,
					"id": 358,
					"legend": {
						"avg": false,
						"current": false,
						"max": false,
						"min": false,
						"show": true,
						"total": false,
						"values": false
					},
					"lines": true,
					"linewidth": 1,
					"nullPointMode": "null",
					"options": {
						"alertThreshold": true
					},
					"percentage": false,
					"pluginVersion": "7.5.4",
					"pointradius": 2,
					"points": false,
					"renderer": "flot",
					"seriesOverrides": [],
					"spaceLength": 10,
					"stack": false,
					"steppedLine": false,
					"targets": [
						{
							"exemplar": true,
							"expr": "irate(node_pressure_cpu_waiting_seconds_total[5m])",
							"interval": "",
							"legendFormat": "{{instance}}",
							"refId": "A"
						}
					],
					"thresholds": [],
					"timeFrom": null,
					"timeRegions": [],
					"timeShift": null,
					"title": "Node Cpu Waiting Seconds Average Over 5m",
					"tooltip": {
						"shared": true,
						"sort": 0,
						"value_type": "individual"
					},
					"type": "graph",
					"xaxis": {
						"buckets": null,
						"mode": "time",
						"name": null,
						"show": true,
						"values": []
					},
					"yaxes": [
						{
							"format": "short",
							"label": null,
							"logBase": 1,
							"max": null,
							"min": null,
							"show": true
						},
						{
							"format": "short",
							"label": null,
							"logBase": 1,
							"max": null,
							"min": null,
							"show": true
						}
					],
					"yaxis": {
						"align": false,
						"alignLevel": null
					}
				}
			],
			"title": "Node Pressure NHD",
			"type": "row"
		},
		{
			"collapsed": true,
			"datasource": "Prometheus",
			"gridPos": {
				"h": 1,
				"w": 24,
				"x": 0,
				"y": 23
			},
			"id": 265,
			"panels": [
				{
					"aliasColors": {
						"Idle - Waiting for something to happen": "#052B51",
						"guest": "#9AC48A",
						"idle": "#052B51",
						"iowait": "#EAB839",
						"irq": "#BF1B00",
						"nice": "#C15C17",
						"softirq": "#E24D42",
						"steal": "#FCE2DE",
						"system": "#508642",
						"user": "#5195CE"
					},
					"bars": false,
					"dashLength": 10,
					"dashes": false,
					"datasource": "Prometheus",
					"decimals": 2,
					"description": "",
					"fieldConfig": {
						"defaults": {
							"links": []
						},
						"overrides": []
					},
					"fill": 4,
					"fillGradient": 0,
					"gridPos": {
						"h": 12,
						"w": 12,
						"x": 0,
						"y": 25
					},
					"hiddenSeries": false,
					"id": 3,
					"legend": {
						"alignAsTable": true,
						"avg": true,
						"current": true,
						"max": true,
						"min": true,
						"rightSide": false,
						"show": true,
						"sideWidth": 250,
						"sort": null,
						"sortDesc": null,
						"total": false,
						"values": true
					},
					"lines": true,
					"linewidth": 1,
					"links": [],
					"maxPerRow": 6,
					"nullPointMode": "null",
					"options": {
						"alertThreshold": true
					},
					"percentage": true,
					"pluginVersion": "7.5.3",
					"pointradius": 5,
					"points": false,
					"renderer": "flot",
					"repeat": null,
					"seriesOverrides": [],
					"spaceLength": 10,
					"stack": true,
					"steppedLine": false,
					"targets": [
						{
							"expr": "sum by (mode)(irate(node_cpu_seconds_total{mode=\"system\",instance=\"$node\",job=\"$job\"}[5m])) * 100",
							"format": "time_series",
							"interval": "10s",
							"intervalFactor": 2,
							"legendFormat": "System - Processes executing in kernel mode",
							"refId": "A",
							"step": 20
						},
						{
							"expr": "sum by (mode)(irate(node_cpu_seconds_total{mode='user',instance=\"$node\",job=\"$job\"}[5m])) * 100",
							"format": "time_series",
							"intervalFactor": 2,
							"legendFormat": "User - Normal processes executing in user mode",
							"refId": "B",
							"step": 240
						},
						{
							"expr": "sum by (mode)(irate(node_cpu_seconds_total{mode='nice',instance=\"$node\",job=\"$job\"}[5m])) * 100",
							"format": "time_series",
							"intervalFactor": 2,
							"legendFormat": "Nice - Niced processes executing in user mode",
							"refId": "C",
							"step": 240
						},
						{
							"expr": "sum by (mode)(irate(node_cpu_seconds_total{mode='idle',instance=\"$node\",job=\"$job\"}[5m])) * 100",
							"format": "time_series",
							"intervalFactor": 2,
							"legendFormat": "Idle - Waiting for something to happen",
							"refId": "D",
							"step": 240
						},
						{
							"expr": "sum by (mode)(irate(node_cpu_seconds_total{mode='iowait',instance=\"$node\",job=\"$job\"}[5m])) * 100",
							"format": "time_series",
							"intervalFactor": 2,
							"legendFormat": "Iowait - Waiting for I/O to complete",
							"refId": "E",
							"step": 240
						},
						{
							"expr": "sum by (mode)(irate(node_cpu_seconds_total{mode='irq',instance=\"$node\",job=\"$job\"}[5m])) * 100",
							"format": "time_series",
							"intervalFactor": 2,
							"legendFormat": "Irq - Servicing interrupts",
							"refId": "F",
							"step": 240
						},
						{
							"expr": "sum by (mode)(irate(node_cpu_seconds_total{mode='softirq',instance=\"$node\",job=\"$job\"}[5m])) * 100",
							"format": "time_series",
							"intervalFactor": 2,
							"legendFormat": "Softirq - Servicing softirqs",
							"refId": "G",
							"step": 240
						},
						{
							"expr": "sum by (mode)(irate(node_cpu_seconds_total{mode='steal',instance=\"$node\",job=\"$job\"}[5m])) * 100",
							"format": "time_series",
							"intervalFactor": 2,
							"legendFormat": "Steal - Time spent in other operating systems when running in a virtualized environment",
							"refId": "H",
							"step": 240
						},
						{
							"expr": "sum by (mode)(irate(node_cpu_seconds_total{mode='guest',instance=\"$node\",job=\"$job\"}[5m])) * 100",
							"format": "time_series",
							"intervalFactor": 2,
							"legendFormat": "Guest - Time spent running a virtual CPU for a guest operating system",
							"refId": "I",
							"step": 240
						}
					],
					"thresholds": [],
					"timeFrom": null,
					"timeRegions": [],
					"timeShift": null,
					"title": "CPU",
					"tooltip": {
						"shared": true,
						"sort": 0,
						"value_type": "individual"
					},
					"type": "graph",
					"xaxis": {
						"buckets": null,
						"mode": "time",
						"name": null,
						"show": true,
						"values": []
					},
					"yaxes": [
						{
							"format": "short",
							"label": "percentage",
							"logBase": 1,
							"max": "100",
							"min": "0",
							"show": true
						},
						{
							"format": "short",
							"label": null,
							"logBase": 1,
							"max": null,
							"min": null,
							"show": false
						}
					],
					"yaxis": {
						"align": false,
						"alignLevel": null
					}
				},
				{
					"aliasColors": {
						"Apps": "#629E51",
						"Buffers": "#614D93",
						"Cache": "#6D1F62",
						"Cached": "#511749",
						"Committed": "#508642",
						"Free": "#0A437C",
						"Hardware Corrupted - Amount of RAM that the kernel identified as corrupted / not working": "#CFFAFF",
						"Inactive": "#584477",
						"PageTables": "#0A50A1",
						"Page_Tables": "#0A50A1",
						"RAM_Free": "#E0F9D7",
						"Slab": "#806EB7",
						"Slab_Cache": "#E0752D",
						"Swap": "#BF1B00",
						"Swap - Swap memory usage": "#BF1B00",
						"Swap_Cache": "#C15C17",
						"Swap_Free": "#2F575E",
						"Unused": "#EAB839",
						"Unused - Free memory unassigned": "#052B51"
					},
					"bars": false,
					"dashLength": 10,
					"dashes": false,
					"datasource": "Prometheus",
					"decimals": 2,
					"description": "",
					"fieldConfig": {
						"defaults": {
							"links": []
						},
						"overrides": []
					},
					"fill": 4,
					"fillGradient": 0,
					"gridPos": {
						"h": 12,
						"w": 12,
						"x": 12,
						"y": 25
					},
					"hiddenSeries": false,
					"id": 24,
					"legend": {
						"alignAsTable": true,
						"avg": true,
						"current": true,
						"max": true,
						"min": true,
						"rightSide": false,
						"show": true,
						"sideWidth": 350,
						"sort": null,
						"sortDesc": null,
						"total": false,
						"values": true
					},
					"lines": true,
					"linewidth": 1,
					"links": [],
					"maxPerRow": 6,
					"nullPointMode": "null",
					"options": {
						"alertThreshold": true
					},
					"percentage": false,
					"pluginVersion": "7.5.3",
					"pointradius": 5,
					"points": false,
					"renderer": "flot",
					"seriesOverrides": [
						{
							"alias": "/.*Hardware Corrupted - *./",
							"stack": false
						}
					],
					"spaceLength": 10,
					"stack": true,
					"steppedLine": false,
					"targets": [
						{
							"expr": "node_memory_MemTotal_bytes{instance=\"$node\",job=\"$job\"} - node_memory_MemFree_bytes{instance=\"$node\",job=\"$job\"} - node_memory_Buffers_bytes{instance=\"$node\",job=\"$job\"} - node_memory_Cached_bytes{instance=\"$node\",job=\"$job\"} - node_memory_Slab_bytes{instance=\"$node\",job=\"$job\"} - node_memory_PageTables_bytes{instance=\"$node\",job=\"$job\"} - node_memory_SwapCached_bytes{instance=\"$node\",job=\"$job\"}",
							"format": "time_series",
							"hide": false,
							"intervalFactor": 2,
							"legendFormat": "Apps - Memory used by user-space applications",
							"refId": "A",
							"step": 240
						},
						{
							"expr": "node_memory_PageTables_bytes{instance=\"$node\",job=\"$job\"}",
							"format": "time_series",
							"hide": false,
							"intervalFactor": 2,
							"legendFormat": "PageTables - Memory used to map between virtual and physical memory addresses",
							"refId": "B",
							"step": 240
						},
						{
							"expr": "node_memory_SwapCached_bytes{instance=\"$node\",job=\"$job\"}",
							"format": "time_series",
							"intervalFactor": 2,
							"legendFormat": "SwapCache - Memory that keeps track of pages that have been fetched from swap but not yet been modified",
							"refId": "C",
							"step": 240
						},
						{
							"expr": "node_memory_Slab_bytes{instance=\"$node\",job=\"$job\"}",
							"format": "time_series",
							"hide": false,
							"intervalFactor": 2,
							"legendFormat": "Slab - Memory used by the kernel to cache data structures for its own use (caches like inode, dentry, etc)",
							"refId": "D",
							"step": 240
						},
						{
							"expr": "node_memory_Cached_bytes{instance=\"$node\",job=\"$job\"}",
							"format": "time_series",
							"hide": false,
							"intervalFactor": 2,
							"legendFormat": "Cache - Parked file data (file content) cache",
							"refId": "E",
							"step": 240
						},
						{
							"expr": "node_memory_Buffers_bytes{instance=\"$node\",job=\"$job\"}",
							"format": "time_series",
							"hide": false,
							"intervalFactor": 2,
							"legendFormat": "Buffers - Block device (e.g. harddisk) cache",
							"refId": "F",
							"step": 240
						},
						{
							"expr": "node_memory_MemFree_bytes{instance=\"$node\",job=\"$job\"}",
							"format": "time_series",
							"hide": false,
							"intervalFactor": 2,
							"legendFormat": "Unused - Free memory unassigned",
							"refId": "G",
							"step": 240
						},
						{
							"expr": "(node_memory_SwapTotal_bytes{instance=\"$node\",job=\"$job\"} - node_memory_SwapFree_bytes{instance=\"$node\",job=\"$job\"})",
							"format": "time_series",
							"hide": false,
							"intervalFactor": 2,
							"legendFormat": "Swap - Swap space used",
							"refId": "H",
							"step": 240
						},
						{
							"expr": "node_memory_HardwareCorrupted_bytes{instance=\"$node\",job=\"$job\"}",
							"format": "time_series",
							"hide": false,
							"intervalFactor": 2,
							"legendFormat": "Hardware Corrupted - Amount of RAM that the kernel identified as corrupted / not working",
							"refId": "I",
							"step": 240
						}
					],
					"thresholds": [],
					"timeFrom": null,
					"timeRegions": [],
					"timeShift": null,
					"title": "Memory Stack",
					"tooltip": {
						"shared": true,
						"sort": 0,
						"value_type": "individual"
					},
					"type": "graph",
					"xaxis": {
						"buckets": null,
						"mode": "time",
						"name": null,
						"show": true,
						"values": []
					},
					"yaxes": [
						{
							"format": "bytes",
							"label": "bytes",
							"logBase": 1,
							"max": null,
							"min": "0",
							"show": true
						},
						{
							"format": "short",
							"label": null,
							"logBase": 1,
							"max": null,
							"min": null,
							"show": false
						}
					],
					"yaxis": {
						"align": false,
						"alignLevel": null
					}
				},
				{
					"aliasColors": {
						"receive_packets_eth0": "#7EB26D",
						"receive_packets_lo": "#E24D42",
						"transmit_packets_eth0": "#7EB26D",
						"transmit_packets_lo": "#E24D42"
					},
					"bars": false,
					"dashLength": 10,
					"dashes": false,
					"datasource": "Prometheus",
					"fieldConfig": {
						"defaults": {
							"links": []
						},
						"overrides": []
					},
					"fill": 4,
					"fillGradient": 0,
					"gridPos": {
						"h": 12,
						"w": 12,
						"x": 0,
						"y": 37
					},
					"hiddenSeries": false,
					"id": 84,
					"legend": {
						"alignAsTable": true,
						"avg": true,
						"current": true,
						"max": true,
						"min": true,
						"rightSide": false,
						"show": true,
						"total": false,
						"values": true
					},
					"lines": true,
					"linewidth": 1,
					"links": [],
					"nullPointMode": "null",
					"options": {
						"alertThreshold": true
					},
					"percentage": false,
					"pluginVersion": "7.5.3",
					"pointradius": 5,
					"points": false,
					"renderer": "flot",
					"seriesOverrides": [
						{
							"$$hashKey": "object:5871",
							"alias": "/.*Trans.*/",
							"transform": "negative-Y"
						}
					],
					"spaceLength": 10,
					"stack": false,
					"steppedLine": false,
					"targets": [
						{
							"expr": "irate(node_network_receive_bytes_total{instance=\"$node\",job=\"$job\"}[5m])*8",
							"format": "time_series",
							"intervalFactor": 2,
							"legendFormat": "{{device}} - Receive",
							"refId": "A",
							"step": 240
						},
						{
							"expr": "irate(node_network_transmit_bytes_total{instance=\"$node\",job=\"$job\"}[5m])*8",
							"format": "time_series",
							"intervalFactor": 2,
							"legendFormat": "{{device}} - Transmit",
							"refId": "B",
							"step": 240
						}
					],
					"thresholds": [],
					"timeFrom": null,
					"timeRegions": [],
					"timeShift": null,
					"title": "Network Traffic",
					"tooltip": {
						"shared": true,
						"sort": 0,
						"value_type": "individual"
					},
					"type": "graph",
					"xaxis": {
						"buckets": null,
						"mode": "time",
						"name": null,
						"show": true,
						"values": []
					},
					"yaxes": [
						{
							"$$hashKey": "object:5884",
							"format": "bps",
							"label": "bits out (-) / in (+)",
							"logBase": 1,
							"max": null,
							"min": null,
							"show": true
						},
						{
							"$$hashKey": "object:5885",
							"format": "short",
							"label": null,
							"logBase": 1,
							"max": null,
							"min": null,
							"show": false
						}
					],
					"yaxis": {
						"align": false,
						"alignLevel": null
					}
				},
				{
					"aliasColors": {},
					"bars": false,
					"dashLength": 10,
					"dashes": false,
					"datasource": "Prometheus",
					"decimals": 3,
					"description": "",
					"fieldConfig": {
						"defaults": {
							"links": []
						},
						"overrides": []
					},
					"fill": 4,
					"fillGradient": 0,
					"gridPos": {
						"h": 12,
						"w": 12,
						"x": 12,
						"y": 37
					},
					"height": "",
					"hiddenSeries": false,
					"id": 156,
					"legend": {
						"alignAsTable": true,
						"avg": true,
						"current": true,
						"max": true,
						"min": true,
						"rightSide": false,
						"show": true,
						"sort": "current",
						"sortDesc": false,
						"total": false,
						"values": true
					},
					"lines": true,
					"linewidth": 1,
					"links": [],
					"maxPerRow": 6,
					"nullPointMode": "null",
					"options": {
						"alertThreshold": true
					},
					"percentage": false,
					"pluginVersion": "7.5.3",
					"pointradius": 5,
					"points": false,
					"renderer": "flot",
					"seriesOverrides": [],
					"spaceLength": 10,
					"stack": false,
					"steppedLine": false,
					"targets": [
						{
							"expr": "node_filesystem_size_bytes{instance=\"$node\",job=\"$job\",device!~'rootfs'} - node_filesystem_avail_bytes{instance=\"$node\",job=\"$job\",device!~'rootfs'}",
							"format": "time_series",
							"intervalFactor": 2,
							"legendFormat": "{{mountpoint}}",
							"refId": "A",
							"step": 240
						}
					],
					"thresholds": [],
					"timeFrom": null,
					"timeRegions": [],
					"timeShift": null,
					"title": "Disk Space Used",
					"tooltip": {
						"shared": true,
						"sort": 0,
						"value_type": "individual"
					},
					"type": "graph",
					"xaxis": {
						"buckets": null,
						"mode": "time",
						"name": null,
						"show": true,
						"values": []
					},
					"yaxes": [
						{
							"format": "bytes",
							"label": "bytes",
							"logBase": 1,
							"max": null,
							"min": "0",
							"show": true
						},
						{
							"format": "short",
							"label": null,
							"logBase": 1,
							"max": null,
							"min": null,
							"show": false
						}
					],
					"yaxis": {
						"align": false,
						"alignLevel": null
					}
				},
				{
					"aliasColors": {},
					"bars": false,
					"dashLength": 10,
					"dashes": false,
					"datasource": "Prometheus",
					"description": "",
					"fieldConfig": {
						"defaults": {
							"links": []
						},
						"overrides": []
					},
					"fill": 2,
					"fillGradient": 0,
					"gridPos": {
						"h": 12,
						"w": 12,
						"x": 0,
						"y": 49
					},
					"hiddenSeries": false,
					"id": 229,
					"legend": {
						"alignAsTable": true,
						"avg": true,
						"current": true,
						"hideZero": true,
						"max": true,
						"min": true,
						"rightSide": false,
						"show": true,
						"total": false,
						"values": true
					},
					"lines": true,
					"linewidth": 1,
					"links": [],
					"maxPerRow": 6,
					"nullPointMode": "null",
					"options": {
						"alertThreshold": true
					},
					"percentage": false,
					"pluginVersion": "7.5.3",
					"pointradius": 5,
					"points": false,
					"renderer": "flot",
					"seriesOverrides": [
						{
							"alias": "/.*Read.*/",
							"transform": "negative-Y"
						},
						{
							"alias": "/.*sda_.*/",
							"color": "#7EB26D"
						},
						{
							"alias": "/.*sdb_.*/",
							"color": "#EAB839"
						},
						{
							"alias": "/.*sdc_.*/",
							"color": "#6ED0E0"
						},
						{
							"alias": "/.*sdd_.*/",
							"color": "#EF843C"
						},
						{
							"alias": "/.*sde_.*/",
							"color": "#E24D42"
						},
						{
							"alias": "/.*sda1.*/",
							"color": "#584477"
						},
						{
							"alias": "/.*sda2_.*/",
							"color": "#BA43A9"
						},
						{
							"alias": "/.*sda3_.*/",
							"color": "#F4D598"
						},
						{
							"alias": "/.*sdb1.*/",
							"color": "#0A50A1"
						},
						{
							"alias": "/.*sdb2.*/",
							"color": "#BF1B00"
						},
						{
							"alias": "/.*sdb2.*/",
							"color": "#BF1B00"
						},
						{
							"alias": "/.*sdb3.*/",
							"color": "#E0752D"
						},
						{
							"alias": "/.*sdc1.*/",
							"color": "#962D82"
						},
						{
							"alias": "/.*sdc2.*/",
							"color": "#614D93"
						},
						{
							"alias": "/.*sdc3.*/",
							"color": "#9AC48A"
						},
						{
							"alias": "/.*sdd1.*/",
							"color": "#65C5DB"
						},
						{
							"alias": "/.*sdd2.*/",
							"color": "#F9934E"
						},
						{
							"alias": "/.*sdd3.*/",
							"color": "#EA6460"
						},
						{
							"alias": "/.*sde1.*/",
							"color": "#E0F9D7"
						},
						{
							"alias": "/.*sdd2.*/",
							"color": "#FCEACA"
						},
						{
							"alias": "/.*sde3.*/",
							"color": "#F9E2D2"
						}
					],
					"spaceLength": 10,
					"stack": false,
					"steppedLine": false,
					"targets": [
						{
							"expr": "irate(node_disk_reads_completed_total{instance=\"$node\",job=\"$job\",device=~\"$diskdevices\"}[5m])",
							"intervalFactor": 4,
							"legendFormat": "{{device}} - Reads completed",
							"refId": "A",
							"step": 480
						},
						{
							"expr": "irate(node_disk_writes_completed_total{instance=\"$node\",job=\"$job\",device=~\"$diskdevices\"}[5m])",
							"intervalFactor": 2,
							"legendFormat": "{{device}} - Writes completed",
							"refId": "B",
							"step": 240
						}
					],
					"thresholds": [],
					"timeFrom": null,
					"timeRegions": [],
					"timeShift": null,
					"title": "Disk IOps",
					"tooltip": {
						"shared": false,
						"sort": 0,
						"value_type": "individual"
					},
					"type": "graph",
					"xaxis": {
						"buckets": null,
						"mode": "time",
						"name": null,
						"show": true,
						"values": []
					},
					"yaxes": [
						{
							"format": "iops",
							"label": "IO read (-) / write (+)",
							"logBase": 1,
							"max": null,
							"min": null,
							"show": true
						},
						{
							"format": "short",
							"label": null,
							"logBase": 1,
							"max": null,
							"min": null,
							"show": false
						}
					],
					"yaxis": {
						"align": false,
						"alignLevel": null
					}
				},
				{
					"aliasColors": {
						"io time": "#890F02"
					},
					"bars": false,
					"dashLength": 10,
					"dashes": false,
					"datasource": "Prometheus",
					"decimals": 3,
					"description": "",
					"fieldConfig": {
						"defaults": {
							"links": []
						},
						"overrides": []
					},
					"fill": 4,
					"fillGradient": 0,
					"gridPos": {
						"h": 12,
						"w": 12,
						"x": 12,
						"y": 49
					},
					"hiddenSeries": false,
					"id": 42,
					"legend": {
						"alignAsTable": true,
						"avg": true,
						"current": true,
						"max": true,
						"min": true,
						"rightSide": false,
						"show": true,
						"sort": null,
						"sortDesc": null,
						"total": false,
						"values": true
					},
					"lines": true,
					"linewidth": 1,
					"links": [],
					"maxPerRow": 6,
					"nullPointMode": "null",
					"options": {
						"alertThreshold": true
					},
					"percentage": false,
					"pluginVersion": "7.5.3",
					"pointradius": 5,
					"points": false,
					"renderer": "flot",
					"seriesOverrides": [
						{
							"alias": "/.*read*./",
							"transform": "negative-Y"
						},
						{
							"alias": "/.*sda.*/",
							"color": "#7EB26D"
						},
						{
							"alias": "/.*sdb.*/",
							"color": "#EAB839"
						},
						{
							"alias": "/.*sdc.*/",
							"color": "#6ED0E0"
						},
						{
							"alias": "/.*sdd.*/",
							"color": "#EF843C"
						},
						{
							"alias": "/.*sde.*/",
							"color": "#E24D42"
						}
					],
					"spaceLength": 10,
					"stack": false,
					"steppedLine": false,
					"targets": [
						{
							"expr": "irate(node_disk_read_bytes_total{instance=\"$node\",job=\"$job\",device=~\"$diskdevices\"}[5m])",
							"format": "time_series",
							"hide": false,
							"intervalFactor": 2,
							"legendFormat": "{{device}} - Successfully read bytes",
							"refId": "A",
							"step": 240
						},
						{
							"expr": "irate(node_disk_written_bytes_total{instance=\"$node\",job=\"$job\",device=~\"$diskdevices\"}[5m])",
							"format": "time_series",
							"hide": false,
							"intervalFactor": 2,
							"legendFormat": "{{device}} - Successfully written bytes",
							"refId": "B",
							"step": 240
						}
					],
					"thresholds": [],
					"timeFrom": null,
					"timeRegions": [],
					"timeShift": null,
					"title": "I/O Usage Read / Write",
					"tooltip": {
						"shared": true,
						"sort": 0,
						"value_type": "individual"
					},
					"type": "graph",
					"xaxis": {
						"buckets": null,
						"mode": "time",
						"name": null,
						"show": false,
						"values": []
					},
					"yaxes": [
						{
							"format": "bytes",
							"label": "bytes read (-) / write (+)",
							"logBase": 1,
							"max": null,
							"min": null,
							"show": true
						},
						{
							"format": "ms",
							"label": "",
							"logBase": 1,
							"max": null,
							"min": null,
							"show": true
						}
					],
					"yaxis": {
						"align": false,
						"alignLevel": null
					}
				},
				{
					"aliasColors": {
						"io time": "#890F02"
					},
					"bars": false,
					"dashLength": 10,
					"dashes": false,
					"datasource": "Prometheus",
					"decimals": 3,
					"description": "",
					"fieldConfig": {
						"defaults": {
							"links": []
						},
						"overrides": []
					},
					"fill": 4,
					"fillGradient": 0,
					"gridPos": {
						"h": 12,
						"w": 12,
						"x": 0,
						"y": 61
					},
					"hiddenSeries": false,
					"id": 127,
					"legend": {
						"alignAsTable": true,
						"avg": true,
						"current": true,
						"max": true,
						"min": true,
						"rightSide": false,
						"show": true,
						"sort": null,
						"sortDesc": null,
						"total": false,
						"values": true
					},
					"lines": true,
					"linewidth": 1,
					"links": [],
					"maxPerRow": 6,
					"nullPointMode": "null",
					"options": {
						"alertThreshold": true
					},
					"percentage": false,
					"pluginVersion": "7.5.3",
					"pointradius": 5,
					"points": false,
					"renderer": "flot",
					"seriesOverrides": [],
					"spaceLength": 10,
					"stack": false,
					"steppedLine": false,
					"targets": [
						{
							"expr": "irate(node_disk_io_time_seconds_total{instance=\"$node\",job=\"$job\",device=~\"$diskdevices\"} [5m])",
							"format": "time_series",
							"hide": false,
							"intervalFactor": 2,
							"legendFormat": "{{device}} - Time spent doing I/Os",
							"refId": "A",
							"step": 240
						}
					],
					"thresholds": [],
					"timeFrom": null,
					"timeRegions": [],
					"timeShift": null,
					"title": "I/O Usage Times",
					"tooltip": {
						"shared": true,
						"sort": 0,
						"value_type": "individual"
					},
					"type": "graph",
					"xaxis": {
						"buckets": null,
						"mode": "time",
						"name": null,
						"show": false,
						"values": []
					},
					"yaxes": [
						{
							"format": "s",
							"label": "time",
							"logBase": 1,
							"max": null,
							"min": "0",
							"show": true
						},
						{
							"format": "s",
							"label": "",
							"logBase": 1,
							"max": null,
							"min": null,
							"show": false
						}
					],
					"yaxis": {
						"align": false,
						"alignLevel": null
					}
				}
			],
			"repeat": null,
			"title": "CPU / Memory / Net / Disk",
			"type": "row"
		},
		{
			"collapsed": true,
			"datasource": "Prometheus",
			"gridPos": {
				"h": 1,
				"w": 24,
				"x": 0,
				"y": 24
			},
			"id": 271,
			"panels": [
				{
					"aliasColors": {},
					"bars": false,
					"dashLength": 10,
					"dashes": false,
					"datasource": "Prometheus",
					"decimals": 3,
					"description": "",
					"fieldConfig": {
						"defaults": {
							"links": []
						},
						"overrides": []
					},
					"fill": 2,
					"fillGradient": 0,
					"gridPos": {
						"h": 10,
						"w": 12,
						"x": 0,
						"y": 6
					},
					"hiddenSeries": false,
					"id": 43,
					"legend": {
						"alignAsTable": true,
						"avg": true,
						"current": true,
						"max": true,
						"min": true,
						"rightSide": false,
						"show": true,
						"total": false,
						"values": true
					},
					"lines": true,
					"linewidth": 1,
					"links": [],
					"maxPerRow": 6,
					"nullPointMode": "null",
					"options": {
						"alertThreshold": true
					},
					"percentage": false,
					"pluginVersion": "7.5.4",
					"pointradius": 5,
					"points": false,
					"renderer": "flot",
					"seriesOverrides": [],
					"spaceLength": 10,
					"stack": false,
					"steppedLine": false,
					"targets": [
						{
							"expr": "node_filesystem_avail_bytes{instance=\"$node\",job=\"$job\",device!~'rootfs'}",
							"format": "time_series",
							"hide": false,
							"intervalFactor": 2,
							"legendFormat": "{{mountpoint}} - Available",
							"metric": "",
							"refId": "A",
							"step": 4
						},
						{
							"expr": "node_filesystem_free_bytes{instance=\"$node\",job=\"$job\",device!~'rootfs'}",
							"format": "time_series",
							"hide": true,
							"intervalFactor": 2,
							"legendFormat": "{{mountpoint}} - Free",
							"refId": "B",
							"step": 2
						},
						{
							"expr": "node_filesystem_size_bytes{instance=\"$node\",job=\"$job\",device!~'rootfs'}",
							"format": "time_series",
							"hide": true,
							"intervalFactor": 2,
							"legendFormat": "{{mountpoint}} - Size",
							"refId": "C",
							"step": 2
						}
					],
					"thresholds": [],
					"timeFrom": null,
					"timeRegions": [],
					"timeShift": null,
					"title": "Filesystem space available",
					"tooltip": {
						"shared": true,
						"sort": 0,
						"value_type": "individual"
					},
					"type": "graph",
					"xaxis": {
						"buckets": null,
						"mode": "time",
						"name": null,
						"show": true,
						"values": []
					},
					"yaxes": [
						{
							"$$hashKey": "object:3826",
							"format": "bytes",
							"label": "bytes",
							"logBase": 1,
							"max": null,
							"min": "0",
							"show": true
						},
						{
							"$$hashKey": "object:3827",
							"format": "short",
							"label": null,
							"logBase": 1,
							"max": null,
							"min": null,
							"show": false
						}
					],
					"yaxis": {
						"align": false,
						"alignLevel": null
					}
				},
				{
					"aliasColors": {},
					"bars": false,
					"dashLength": 10,
					"dashes": false,
					"datasource": "Prometheus",
					"description": "",
					"fieldConfig": {
						"defaults": {
							"links": []
						},
						"overrides": []
					},
					"fill": 2,
					"fillGradient": 0,
					"gridPos": {
						"h": 10,
						"w": 12,
						"x": 12,
						"y": 6
					},
					"hiddenSeries": false,
					"id": 41,
					"legend": {
						"alignAsTable": true,
						"avg": true,
						"current": true,
						"hideZero": true,
						"max": true,
						"min": true,
						"rightSide": false,
						"show": true,
						"total": false,
						"values": true
					},
					"lines": true,
					"linewidth": 1,
					"links": [],
					"nullPointMode": "null",
					"options": {
						"alertThreshold": true
					},
					"percentage": false,
					"pluginVersion": "7.5.4",
					"pointradius": 5,
					"points": false,
					"renderer": "flot",
					"seriesOverrides": [],
					"spaceLength": 10,
					"stack": false,
					"steppedLine": false,
					"targets": [
						{
							"expr": "node_filesystem_files_free{instance=\"$node\",job=\"$job\",device!~'rootfs'}",
							"format": "time_series",
							"hide": false,
							"intervalFactor": 2,
							"legendFormat": "{{mountpoint}} - Free file nodes",
							"refId": "A",
							"step": 4
						}
					],
					"thresholds": [],
					"timeFrom": null,
					"timeRegions": [],
					"timeShift": null,
					"title": "File Nodes Free",
					"tooltip": {
						"shared": true,
						"sort": 0,
						"value_type": "individual"
					},
					"type": "graph",
					"xaxis": {
						"buckets": null,
						"mode": "time",
						"name": null,
						"show": true,
						"values": []
					},
					"yaxes": [
						{
							"$$hashKey": "object:3894",
							"format": "short",
							"label": "file nodes",
							"logBase": 1,
							"max": null,
							"min": "0",
							"show": true
						},
						{
							"$$hashKey": "object:3895",
							"format": "short",
							"label": null,
							"logBase": 1,
							"max": null,
							"min": null,
							"show": false
						}
					],
					"yaxis": {
						"align": false,
						"alignLevel": null
					}
				},
				{
					"aliasColors": {},
					"bars": false,
					"dashLength": 10,
					"dashes": false,
					"datasource": "Prometheus",
					"description": "",
					"fieldConfig": {
						"defaults": {
							"links": []
						},
						"overrides": []
					},
					"fill": 2,
					"fillGradient": 0,
					"gridPos": {
						"h": 10,
						"w": 12,
						"x": 0,
						"y": 16
					},
					"hiddenSeries": false,
					"id": 28,
					"legend": {
						"alignAsTable": true,
						"avg": true,
						"current": true,
						"max": true,
						"min": true,
						"show": true,
						"total": false,
						"values": true
					},
					"lines": true,
					"linewidth": 1,
					"links": [],
					"maxPerRow": 6,
					"nullPointMode": "null",
					"options": {
						"alertThreshold": true
					},
					"percentage": false,
					"pluginVersion": "7.5.4",
					"pointradius": 5,
					"points": false,
					"renderer": "flot",
					"seriesOverrides": [],
					"spaceLength": 10,
					"stack": false,
					"steppedLine": false,
					"targets": [
						{
							"expr": "node_filefd_maximum{instance=\"$node\",job=\"$job\"}",
							"format": "time_series",
							"intervalFactor": 4,
							"legendFormat": "Max open files",
							"refId": "A",
							"step": 8
						},
						{
							"expr": "node_filefd_allocated{instance=\"$node\",job=\"$job\"}",
							"format": "time_series",
							"intervalFactor": 2,
							"legendFormat": "Open files",
							"refId": "B",
							"step": 4
						}
					],
					"thresholds": [],
					"timeFrom": null,
					"timeRegions": [],
					"timeShift": null,
					"title": "File Descriptor",
					"tooltip": {
						"shared": false,
						"sort": 0,
						"value_type": "individual"
					},
					"type": "graph",
					"xaxis": {
						"buckets": null,
						"mode": "time",
						"name": null,
						"show": true,
						"values": []
					},
					"yaxes": [
						{
							"format": "short",
							"label": "files",
							"logBase": 1,
							"max": null,
							"min": "0",
							"show": true
						},
						{
							"format": "short",
							"label": null,
							"logBase": 1,
							"max": null,
							"min": null,
							"show": false
						}
					],
					"yaxis": {
						"align": false,
						"alignLevel": null
					}
				},
				{
					"aliasColors": {},
					"bars": false,
					"dashLength": 10,
					"dashes": false,
					"datasource": "Prometheus",
					"description": "",
					"fieldConfig": {
						"defaults": {
							"links": []
						},
						"overrides": []
					},
					"fill": 2,
					"fillGradient": 0,
					"gridPos": {
						"h": 10,
						"w": 12,
						"x": 12,
						"y": 16
					},
					"hiddenSeries": false,
					"id": 219,
					"legend": {
						"alignAsTable": true,
						"avg": true,
						"current": true,
						"hideZero": true,
						"max": true,
						"min": true,
						"rightSide": false,
						"show": true,
						"total": false,
						"values": true
					},
					"lines": true,
					"linewidth": 1,
					"links": [],
					"nullPointMode": "null",
					"options": {
						"alertThreshold": true
					},
					"percentage": false,
					"pluginVersion": "7.5.4",
					"pointradius": 5,
					"points": false,
					"renderer": "flot",
					"seriesOverrides": [],
					"spaceLength": 10,
					"stack": false,
					"steppedLine": false,
					"targets": [
						{
							"expr": "node_filesystem_files{instance=\"$node\",job=\"$job\",device!~'rootfs'}",
							"format": "time_series",
							"hide": false,
							"intervalFactor": 2,
							"legendFormat": "{{mountpoint}} - File nodes total",
							"refId": "A",
							"step": 4
						}
					],
					"thresholds": [],
					"timeFrom": null,
					"timeRegions": [],
					"timeShift": null,
					"title": "File Nodes Size",
					"tooltip": {
						"shared": true,
						"sort": 0,
						"value_type": "individual"
					},
					"type": "graph",
					"xaxis": {
						"buckets": null,
						"mode": "time",
						"name": null,
						"show": true,
						"values": []
					},
					"yaxes": [
						{
							"format": "short",
							"label": "file Nodes",
							"logBase": 1,
							"max": null,
							"min": "0",
							"show": true
						},
						{
							"format": "short",
							"label": null,
							"logBase": 1,
							"max": null,
							"min": null,
							"show": false
						}
					],
					"yaxis": {
						"align": false,
						"alignLevel": null
					}
				},
				{
					"aliasColors": {
						"/ ReadOnly": "#890F02"
					},
					"bars": false,
					"dashLength": 10,
					"dashes": false,
					"datasource": "Prometheus",
					"decimals": null,
					"description": "",
					"fieldConfig": {
						"defaults": {
							"links": []
						},
						"overrides": []
					},
					"fill": 2,
					"fillGradient": 0,
					"gridPos": {
						"h": 10,
						"w": 12,
						"x": 0,
						"y": 26
					},
					"hiddenSeries": false,
					"id": 44,
					"legend": {
						"alignAsTable": true,
						"avg": true,
						"current": true,
						"hideEmpty": true,
						"hideZero": true,
						"max": true,
						"min": true,
						"rightSide": false,
						"show": true,
						"total": false,
						"values": true
					},
					"lines": true,
					"linewidth": 1,
					"links": [],
					"maxPerRow": 6,
					"nullPointMode": "null",
					"options": {
						"alertThreshold": true
					},
					"percentage": false,
					"pluginVersion": "7.5.4",
					"pointradius": 5,
					"points": false,
					"renderer": "flot",
					"seriesOverrides": [],
					"spaceLength": 10,
					"stack": true,
					"steppedLine": false,
					"targets": [
						{
							"expr": "node_filesystem_readonly{instance=\"$node\",job=\"$job\",device!~'rootfs'}",
							"format": "time_series",
							"intervalFactor": 2,
							"legendFormat": "{{mountpoint}} - ReadOnly",
							"refId": "A",
							"step": 4
						},
						{
							"expr": "node_filesystem_device_error{instance=\"$node\",job=\"$job\",device!~'rootfs',fstype!~'tmpfs'}",
							"format": "time_series",
							"interval": "",
							"intervalFactor": 2,
							"legendFormat": "{{mountpoint}} - Device error",
							"refId": "B",
							"step": 4
						}
					],
					"thresholds": [],
					"timeFrom": null,
					"timeRegions": [],
					"timeShift": null,
					"title": "Filesystem in ReadOnly / Error",
					"tooltip": {
						"shared": true,
						"sort": 0,
						"value_type": "individual"
					},
					"type": "graph",
					"xaxis": {
						"buckets": null,
						"mode": "time",
						"name": null,
						"show": true,
						"values": []
					},
					"yaxes": [
						{
							"$$hashKey": "object:3670",
							"format": "short",
							"label": "counter",
							"logBase": 1,
							"max": "1",
							"min": "0",
							"show": true
						},
						{
							"$$hashKey": "object:3671",
							"format": "short",
							"label": null,
							"logBase": 1,
							"max": null,
							"min": null,
							"show": false
						}
					],
					"yaxis": {
						"align": false,
						"alignLevel": null
					}
				}
			],
			"repeat": null,
			"title": "Storage Filesystem",
			"type": "row"
		}
	],
	"refresh": "5s",
	"schemaVersion": 27,
	"style": "dark",
	"tags": [
		"linux",
		"node-exporter",
		"cadvisor"
	],
	"templating": {
		"list": [
			{
				"current": {
					"selected": false,
					"text": "Prometheus",
					"value": "Prometheus"
				},
				"description": null,
				"error": null,
				"hide": 0,
				"includeAll": false,
				"label": "datasource",
				"multi": false,
				"name": "DS_PROMETHEUS",
				"options": [],
				"query": "prometheus",
				"queryValue": "",
				"refresh": 1,
				"regex": "",
				"skipUrlSync": false,
				"type": "datasource"
			},
			{
				"allValue": null,
				"current": {
					"selected": false,
					"text": "kubernetes-pods",
					"value": "kubernetes-pods"
				},
				"datasource": null,
				"definition": "label_values(node_uname_info, job)",
				"description": null,
				"error": {
					"config": {
						"headers": {
							"X-Grafana-Org-Id": 1
						},
						"hideFromInspector": true,
						"method": "GET",
						"retry": 0,
						"url": "api/datasources/proxy/1/api/v1/series?match%5B%5D=node_uname_info&start=1629488135&end=1629489005"
					},
					"data": {
						"error": "Bad Gateway",
						"message": "Bad Gateway",
						"response": ""
					},
					"message": "Bad Gateway",
					"status": 502,
					"statusText": "Bad Gateway"
				},
				"hide": 0,
				"includeAll": false,
				"label": "Job",
				"multi": false,
				"name": "job",
				"options": [],
				"query": {
					"query": "label_values(node_uname_info, job)",
					"refId": "StandardVariableQuery"
				},
				"refresh": 1,
				"regex": "",
				"skipUrlSync": false,
				"sort": 0,
				"tagValuesQuery": "",
				"tags": [],
				"tagsQuery": "",
				"type": "query",
				"useTags": false
			},
			{
				"allValue": null,
				"current": {
					"selected": true,
					"text": "10.200.11.103:9100",
					"value": "10.200.11.103:9100"
				},
				"datasource": "Prometheus",
				"definition": "label_values(node_uname_info{job=\"$job\"}, instance)",
				"description": null,
				"error": {
					"config": {
						"headers": {
							"X-Grafana-Org-Id": 1
						},
						"hideFromInspector": true,
						"method": "GET",
						"retry": 0,
						"url": "api/datasources/proxy/1/api/v1/series?match%5B%5D=node_uname_info%7Bjob%3D%22kubernetes-pods%22%7D&start=1629488135&end=1629489005"
					},
					"data": {
						"error": "Bad Gateway",
						"message": "Bad Gateway",
						"response": ""
					},
					"message": "Bad Gateway",
					"status": 502,
					"statusText": "Bad Gateway"
				},
				"hide": 0,
				"includeAll": false,
				"label": "Host:",
				"multi": false,
				"name": "node",
				"options": [],
				"query": {
					"query": "label_values(node_uname_info{job=\"$job\"}, instance)",
					"refId": "StandardVariableQuery"
				},
				"refresh": 1,
				"regex": "",
				"skipUrlSync": false,
				"sort": 1,
				"tagValuesQuery": "",
				"tags": [],
				"tagsQuery": "",
				"type": "query",
				"useTags": false
			},
			{
				"allValue": null,
				"current": {
					"selected": false,
					"text": "[a-z]+|nvme[0-9]+n[0-9]+",
					"value": "[a-z]+|nvme[0-9]+n[0-9]+"
				},
				"description": null,
				"error": null,
				"hide": 2,
				"includeAll": false,
				"label": null,
				"multi": false,
				"name": "diskdevices",
				"options": [
					{
						"selected": true,
						"text": "[a-z]+|nvme[0-9]+n[0-9]+",
						"value": "[a-z]+|nvme[0-9]+n[0-9]+"
					}
				],
				"query": "[a-z]+|nvme[0-9]+n[0-9]+",
				"skipUrlSync": false,
				"type": "custom"
			},
			{
				"allValue": null,
				"current": {
					"selected": false,
					"text": "cyclonis",
					"value": "cyclonis"
				},
				"datasource": null,
				"definition": "label_values(container_last_seen, container_label_io_kubernetes_pod_namespace)",
				"description": "Namespace for the logs",
				"error": {
					"config": {
						"headers": {
							"X-Grafana-Org-Id": 1
						},
						"hideFromInspector": true,
						"method": "GET",
						"retry": 0,
						"url": "api/datasources/proxy/1/api/v1/series?match%5B%5D=container_last_seen&start=1629488255&end=1629489125"
					},
					"data": {
						"error": "Bad Gateway",
						"message": "Bad Gateway",
						"response": ""
					},
					"message": "Bad Gateway",
					"status": 502,
					"statusText": "Bad Gateway"
				},
				"hide": 0,
				"includeAll": false,
				"label": "Namespace",
				"multi": false,
				"name": "namespace",
				"options": [],
				"query": {
					"query": "label_values(container_last_seen, container_label_io_kubernetes_pod_namespace)",
					"refId": "StandardVariableQuery"
				},
				"refresh": 2,
				"regex": "",
				"skipUrlSync": false,
				"sort": 1,
				"tagValuesQuery": "",
				"tags": [],
				"tagsQuery": "",
				"type": "query",
				"useTags": false
			}
		]
	},
	"time": {
		"from": "now-15m",
		"to": "now-30s"
	},
	"timepicker": {
		"nowDelay": "0m",
		"refresh_intervals": [
			"5s",
			"10s",
			"30s",
			"1m",
			"5m",
			"15m",
			"30m",
			"1h",
			"2h",
			"1d"
		],
		"time_options": [
			"5m",
			"15m",
			"1h",
			"6h",
			"12h",
			"24h",
			"2d",
			"7d",
			"30d"
		]
	},
	"timezone": "browser",
	"title": "Kubernetes Server Metrics",
	"uid": "rYdddlPWk",
	"version": 2
}